pydivar/__init__.py
pydivar/detail.py
pydivar/list.py
pydivar/core/__init__.py
pydivar/core/base.py
pydivar/core/info.py
pydivar-0.1.0.dist-info/LICENSE
pydivar-0.1.0.dist-info/METADATA
pydivar-0.1.0.dist-info/WHEEL
pydivar-0.1.0.dist-info/top_level.txt
pydivar-0.1.0.dist-info/RECORD
